struction
