Metadata-Version: 1.1
Name: Struction
Version: 0.3.0
Summary: Pythonic, yet C-style structs.
Home-page: http://github.com/reshanie/struction
Author: Patrick Dill
Author-email: jamespatrickdill@gmail.com
License: MIT
Download-URL: http://github.com/reshanie/struction/archive/master.tar.gz
Keywords: structs struct datastructure data
Platform: UNKNOWN
Classifier: Development Status :: 4 - Beta
Classifier: Intended Audience :: Developers
Classifier: Programming Language :: Python :: 3
Classifier: Programming Language :: Python :: 3.0
Classifier: Programming Language :: Python :: 3.1
Classifier: Programming Language :: Python :: 3.2
Classifier: Programming Language :: Python :: 3.3
Classifier: Programming Language :: Python :: 3.4
Classifier: Programming Language :: Python :: 3.5
Classifier: Programming Language :: Python :: 3.6
Classifier: Intended Audience :: Developers
